Workbook

Sheet Skills
A1: ID | B1: Skill / SOP | C1: Category | D1: Type | E1: Campaign type | F1: Phase | G1: Account maturity | H1: Cadence | I1: Priority | J1: Use when | K1: Origin / source | L1: Status | M1: Owner | N1: Folder link | O1: Notes | P1: Last verified | Q1: Invalidated by | R1: Canon strength | S1: Review
A2: 1 | B2: Alpha/Beta campaign structure | C2: Account structure | D2: Structure | E2: Search | F2: Scale | G2: Established | H2: One-off | I2: P2 | J2: Search terms report is rich but exact-match coverage is thin; want to harvest winners into exact | K2: Practitioner method | L2: Done | N2: skills/1-alpha-beta-structure/ | P2: 2026-10-13 | Q2: Further loosening or removal of exact match (AI Max replacing keywords); removal of campaign-level negatives; Google giving exact keywords strict cross-campaign priority. | R2: Adequate | S2: PASS
A3: 2 | B3: Hagakure consolidated structure | C3: Account structure | D3: Structure | E3: Search | F3: Setup | G3: Any | H3: One-off | I3: P1 | J3: Moving to Smart Bidding on a fragmented account; too many thin ad groups | K3: Google Japan | L3: Done | N3: skills/2-hagakure-consolidated-structure/ | P3: 2026-10-13 | Q3: Removal of keyword match types or DSA (AI Max replacing keyword targeting); change to Smart Bidding minimum-data guidance; portfolio-level data pooling becoming default. | R3: Strong | S3: PASS
A4: 3 | B4: SKAG vs STAG vs intent-themed ad groups | C4: Account structure | D4: Strategy | E4: Search | F4: Setup | G4: Any | H4: One-off | I4: P2 | J4: Deciding ad group granularity for a new build or restructure | K4: Practitioner debate | L4: Done | N4: skills/3-skag-stag-intent-ad-groups/ | P4: 2026-10-13 | Q4: AI Max or similar fully replacing keyword targeting; RSA serving no longer keying headline 1 to ad-group keywords. | R4: Strong | S4: PASS
A5: 4 | B5: Match-type-split campaigns with cross-negatives | C5: Account structure | D5: Structure | E5: Search | F5: Setup | G5: Established | H5: One-off | I5: P2 | J5: Need separate budgets/bids per match type; phrase is cannibalising exact | K5: Practitioner method | L5: Done | N5: skills/4-match-type-split-campaigns/ | P5: 2026-10-13 | Q5: Removal of match types (AI Max replacing keywords); budgets/targets becoming settable at ad-group level; Google giving exact strict cross-campaign priority. | R5: Adequate | S5: PASS
A6: 5 | B6: Brand/non-brand firewalling (negative mesh) | C6: Account structure | D6: Structure | E6: Search | F6: Setup | G6: Any | H6: One-off | I6: P1 | J6: Brand terms leaking into non-brand campaigns and inflating ROAS | K6: Practitioner method | L6: Done | N6: skills/5-brand-nonbrand-firewall/ | P6: 2026-10-13 | Q6: Brand exclusions reliably catching typos and variants and extending to Standard Shopping; removal of campaign-level negatives in PMax; AI Max replacing keyword Search so negatives stop gating serving. | R6: Adequate | S6: PASS
A7: 6 | B7: Tiered campaign priorities for Shopping | C7: Account structure | D7: Structure | E7: Shopping | F7: Setup | G7: Any | H7: One-off | I7: P2 | J7: Running Standard Shopping and want query-level control | K7: Practitioner method | L7: Drafting | N7: skills/6-tiered-shopping-priorities/ | O7: THIN CANON stub — see SKILL.md question for Elias | P7: 2026-10-13 | Q7: Removal of campaign priority from Standard Shopping; Standard Shopping retired in favour of PMax; brand lists available in Standard Shopping. | R7: Thin | S7: NEEDS ELIAS
A8: 7 | B8: Geo-split campaigns vs. bid adjustments | C8: Account structure | D8: Strategy | E8: All | F8: Setup | G8: Any | H8: As needed | I8: P3 | J8: Markets need separate budgets or messaging; deciding split vs. adjustment | K8: Practitioner method | L8: Done | N8: skills/7-geo-split-vs-bid-adjustments/ | P8: 2026-10-13 | Q8: Google re-enabling location bid adjustments under Smart Bidding; ad-group-level location targeting; per-geo budget allocation inside one campaign. | R8: Adequate | S8: PASS
A9: 8 | B9: Mirror campaigns for Smart Bidding A/B | C9: Account structure | D9: Strategy | E9: Search | F9: Optimise | G9: Established | H9: As needed | I9: P3 | J9: Want to compare bid strategies; deciding mirror vs. custom experiment | K9: Practitioner method | L9: Done | N9: skills/8-mirror-campaigns-bid-strategy-ab/ | P9: 2026-10-13 | Q9: Custom experiments extended to Shopping/PMax and shared budgets; experiments syncing base-campaign changes; a Smart Bidding learning change that removes the 2–3-week stabilisation. | R9: Adequate | S9: PASS
A10: 9 | B10: Micro-campaign consolidation for low-volume accounts | C10: Account structure | D10: Strategy | E10: Search | F10: Diagnose | G10: New | H10: One-off | I10: P2 | J10: Campaigns stuck in learning; <15–30 conv/month per campaign | K10: Practitioner method | L10: Done | N10: skills/9-micro-campaign-consolidation/ | P10: 2026-10-13 | Q10: Bid limits exposed on campaign-level tCPA; Smart Bidding learning changes that stabilise low-volume campaigns; removal of secondary/soft conversion goals. | R10: Strong | S10: PASS
A11: 10 | B11: N-gram analysis of search terms | C11: Keyword & query | D11: Technique | E11: Search | F11: Optimise | G11: Established | H11: Monthly | I11: P1 | J11: Large search terms report; need to find patterns rather than single terms | K11: Scripts community | L11: Done | N11: skills/10-n-gram-analysis/ | P11: 2026-10-13 | Q11: Further cuts to search terms report visibility; negative keywords starting to match close variants or synonyms; Scripts/GAQL changes to the search_term_view resource; removal of PMax search term reporting. | R11: Strong | S11: PASS
A12: 11 | B12: Close-variant leakage audit | C12: Keyword & query | D12: Diagnostic | E12: Search | F12: Diagnose | G12: Any | H12: Monthly | I12: P1 | J12: Exact-match CPA drifting; suspect Google is stretching match | K12: Practitioner method | L12: Done | N12: skills/11-close-variant-leakage-audit/ | P12: 2026-10-13 | Q12: Removal of the "(close variant)" label from the search terms report; keyword prioritisation changes that make identical exact keywords reliably win; negatives beginning to match close variants or synonyms; further search-term visibility cuts. | R12: Strong | S12: PASS
A13: 12 | B13: Negative keyword sculpting across campaigns | C13: Keyword & query | D13: Technique | E13: Search | F13: Optimise | G13: Established | H13: As needed | I13: P1 | J13: Same query matching in several campaigns; routing traffic to the right one | K13: Practitioner method | L13: Done | N13: skills/12-negative-keyword-sculpting/ | P13: 2026-10-13 | Q13: Google changing keyword prioritisation so identical keywords always win regardless of campaign restrictions; negatives starting to match close variants; removal of campaign-level PMax negatives; AI Max replacing keyword-level control in Search (DSA auto-upgrade to AI Max scheduled Feb 2027). | R13: Strong | S13: PASS
A14: 13 | B14: Keyword funnelling via tiered negatives | C14: Keyword & query | D14: Technique | E14: Search | F14: Setup | G14: Established | H14: One-off | I14: P2 | J14: Broad/phrase/exact live side by side; want deterministic routing | K14: Practitioner method | L14: Done | N14: skills/13-keyword-funnelling-tiered-negatives/ | P14: 2026-10-13 | Q14: Keyword prioritisation changes removing identical-exact priority; negatives matching close variants; retirement of exact or phrase match; changes to the low-search-volume threshold or the 13-month zero-impression auto-pause. | R14: Strong | S14: PASS
A15: 14 | B15: DSA as a long-tail harvesting engine | C15: Keyword & query | D15: Strategy | E15: Search | F15: Scale | G15: Established | H15: One-off | I15: P2 | J15: Large site, keyword coverage incomplete; want query discovery | K15: Practitioner method | L15: Done | N15: skills/14-dsa-long-tail-harvesting/ | P15: 2026-10-13 | Q15: The scheduled February 2027 automatic upgrade of DSA campaigns to AI Max; removal of DSA search term reporting; changes to keyword prioritisation between DSA/AI Max and keyword campaigns. | R15: Adequate | S15: PASS
A16: 15 | B16: Competitor conquesting | C16: Keyword & query | D16: Strategy | E16: Search | F16: Scale | G16: Established | H16: As needed | I16: P3 | J16: Considering bidding on competitor brand terms | K16: Practitioner method | L16: Done | N16: skills/15-competitor-conquesting/ | P16: 2026-10-13 | Q16: Changes to Google's brand list / brand exclusion features; trademark policy changes on competitor names in ads; removal of bid caps or CPC floors from portfolio strategies; AI Max removing keyword-level control over competitor terms. | R16: Adequate | S16: PASS
A17: 16 | B17: Broad match + Smart Bidding guardrails | C17: Keyword & query | D17: Research | E17: Search | F17: Scale | G17: Established | H17: One-off | I17: P1 | J17: Testing broad match; need the evidence and the guardrails before rollout | K17: Optmyzr / Google research | L17: Done | N17: skills/16-broad-match-smart-bidding-guardrails/ | P17: 2026-10-13 | Q17: Google removing phrase or exact match or folding Search into AI Max by default; changes to the signals broad match uses (landing page, ad group keywords, recent searches); Smart Bidding learning thresholds changing; search terms visibility cuts that prevent policing broad. | R17: Strong | S17: PASS
A18: 17 | B18: Search partners & Display expansion exclusion test | C18: Keyword & query | D18: Setting | E18: Search | F18: Setup | G18: Any | H18: One-off | I18: P2 | J18: New campaign or auditing an inherited one | K18: Practitioner method | L18: Done | N18: skills/17-search-partners-display-expansion/ | P18: 2026-10-13 | Q18: Google adding per-partner reporting or exclusions; removal of the campaign-level partner toggle; another change to the partner auction like the November 2021 position-first move; Google documenting Display Expansion behaviour differently from the assumption stated below. | R18: Adequate | S18: PASS
A19: 18 | B19: Keyword insertion case variants and DKI risks | C19: Keyword & query | D19: Technique | E19: Search | F19: Optimise | G19: Any | H19: As needed | I19: P3 | J19: Considering DKI; large keyword lists with uniform intent | K19: Google docs + practitioner | L19: Drafting | N19: skills/18-dki-case-variants-risks/ | O19: THIN CANON stub — see SKILL.md question for Elias | P19: 2026-10-13 | Q19: Google changing keyword insertion syntax or removing it from RSAs; trademark policy changes on inserted keywords. | R19: Thin | S19: NEEDS ELIAS
A20: 19 | B20: Low search volume / rarely shown keyword handling | C20: Keyword & query | D20: Diagnostic | E20: Search | F20: Diagnose | G20: Any | H20: As needed | I20: P3 | J20: Keywords flagged low volume or rarely shown | K20: Practitioner method | L20: Done | N20: skills/19-low-search-volume-handling/ | P20: 2026-10-13 | Q20: Google changing the low-search-volume threshold or review cadence; changes to the 13-month zero-impression ad-group auto-pause; changes to PMax routing of low-volume keywords; retirement of exact match. | R20: Adequate | S20: PASS
A21: 20 | B21: Intent-tier keyword taxonomy with per-tier bidding | C21: Keyword & query | D21: Strategy | E21: Search | F21: Setup | G21: Any | H21: One-off | I21: P2 | J21: Building keyword lists; want bidding to follow intent | K21: Practitioner method | L21: Done | N21: skills/20-intent-tier-keyword-taxonomy/ | P21: 2026-10-13 | Q21: Removal of campaign-level bid targets and budgets; removal of conversion values or primary/secondary conversion actions; AI Max replacing keyword-level control in Search campaigns. | R21: Adequate | S21: PASS
A22: 21 | B22: Negative keyword conflict detection | C22: Keyword & query | D22: Diagnostic | E22: Search | F22: Diagnose | G22: Any | H22: Monthly | I22: P2 | J22: Impressions dropped after adding negatives; routine hygiene | K22: Scripts community | L22: Done | N22: skills/21-negative-keyword-conflict-detection/ | P22: 2026-10-13 | Q22: Negatives starting to match close variants or synonyms (changes what a conflict is); Google Ads Scripts API changes breaking keyword/negative/shared-set queries; Google's built-in conflict recommendation starting to cover shared lists and match types. | R22: Adequate | S22: PASS
A23: 22 | B23: RSA iteration loop | C23: RSA & ad copy | D23: Technique | E23: Search | F23: Optimise | G23: Any | H23: Monthly | I23: P1 | J23: Ongoing ad copy improvement; the core testing cadence | K23: Epiminds method | L23: Done | N23: skills/22-rsa-iteration-loop/ | P23: 2026-10-13 | Q23: Removal of asset-level click and conversion reporting; change to the 15/4 asset limits or the always-shown H1/H2/D1 slots; AI Max text customisation becoming mandatory for Search. | R23: Strong | S23: PASS
A24: 23 | B24: Write compelling RSAs | C24: RSA & ad copy | D24: Technique | E24: Search | F24: Setup | G24: Any | H24: As needed | I24: P1 | J24: Writing new RSAs or rewriting underperformers | K24: Epiminds method | L24: Done | N24: skills/23-write-compelling-rsas/ | P24: 2026-10-13 | Q24: Change to the 30/90 character limits or to which slots are always shown; Google routinely serving more than three headlines; mandatory AI Max text assets in Search. | R24: Strong | S24: PASS
A25: 24 | B25: Pinning strategies | C25: RSA & ad copy | D25: Strategy | E25: Search | F25: Optimise | G25: Any | H25: As needed | I25: P1 | J25: Need message control (compliance, offer) vs. letting Google combine | K25: Practitioner method | L25: Done | N25: skills/24-pinning-strategies/ | P25: 2026-10-13 | Q25: Change to which positions are guaranteed to show (H1/H2/D1); pins allowed beyond three headline positions; unpinned serving made mandatory under AI Max. | R25: Strong | S25: PASS
A26: 25 | B26: Ad Strength doesn't predict performance | C26: RSA & ad copy | D26: Research | E26: Search | F26: Optimise | G26: Any | H26: One-off | I26: P2 | J26: Pressure to chase Excellent ad strength; deciding what to optimise instead | K26: Optmyzr study | L26: Done | N26: skills/25-ad-strength-not-performance/ | P26: 2026-10-13 | Q26: Google replacing Ad Strength with a performance-based score, or using it in Ad Rank or serving eligibility. | R26: Strong | S26: PASS
A27: 26 | B27: Combinations report & asset ratings — what they hide | C27: RSA & ad copy | D27: Diagnostic | E27: Search | F27: Diagnose | G27: Established | H27: Monthly | I27: P2 | J27: Reviewing RSA assets; deciding what to replace | K27: Practitioner method | L27: Done | N27: skills/26-combinations-and-asset-stats/ | P27: 2026-10-13 | Q27: Google exposing per-combination clicks and conversions; removal of asset-level statistics; return of a performance-label column as the only asset signal. | R27: Strong | S27: PASS
A28: 27 | B28: Ad variations tool for account-wide copy tests | C28: RSA & ad copy | D28: Technique | E28: Search | F28: Optimise | G28: Established | H28: As needed | I28: P3 | J28: Want to test one change (CTA, price, claim) across many ads | K28: Google docs + practitioner | L28: Done | N28: skills/27-ad-variations-account-wide-tests/ | P28: 2026-10-13 | Q28: Google removing or redesigning Ad variations; removal of asset-level statistics; change to the 3-RSA-per-ad-group limit. | R28: Adequate | S28: PASS
A29: 28 | B29: Keyword-level ad customizers | C29: RSA & ad copy | D29: Technique | E29: Search | F29: Scale | G29: Established | H29: One-off | I29: P2 | J29: Many keywords with distinct prices/variants; want 1:1 copy at scale | K29: Google docs + practitioner | L29: Done | N29: skills/28-keyword-level-ad-customizers/ | P29: 2026-10-13 | Q29: Changes to customizer precedence or the 40-attribute cap; removal of keyword-level customizers; AI Max text customisation overriding advertiser customizer values. | R29: Adequate | S29: PASS
A30: 29 | B30: Dynamic ad customizers (countdown, location, business data) | C30: RSA & ad copy | D30: Technique | E30: Search | F30: Scale | G30: Established | H30: One-off | I30: P2 | J30: Promotions with deadlines, multi-location, or feed-driven copy | K30: Google docs + practitioner | L30: Done | N30: skills/29-dynamic-ad-customizers/ | P30: 2026-10-13 | Q30: Changes to COUNTDOWN/LOCATION syntax or fallback behaviour; removal of business-data customizers; AI Max text customisation overriding advertiser customizer values. | R30: Adequate | S30: PASS
A31: 30 | B31: Campaign-name-as-headline diagnostic trick | C31: RSA & ad copy | D31: Diagnostic | E31: Search | F31: Diagnose | G31: Any | H31: As needed | I31: P3 | J31: Need to know which ad group/campaign a query actually fires from | K31: Practitioner method | L31: Drafting | N31: skills/30-campaign-name-headline-diagnostic/ | O31: THIN CANON stub — see SKILL.md question for Elias | P31: 2026-10-13 | Q31: Not applicable until a method exists; any method depends on the 15-character path fields and the always-shown H1/H2/D1 slots. | R31: Thin | S31: NEEDS ELIAS
A32: 31 | B32: One vs. two RSAs per ad group under Smart Bidding | C32: RSA & ad copy | D32: Research | E32: Search | F32: Setup | G32: Any | H32: One-off | I32: P3 | J32: Deciding ad count per ad group | K32: Practitioner debate | L32: Done | N32: skills/31-one-vs-two-rsas/ | P32: 2026-10-13 | Q32: A change to the per-ad-group RSA limit; removal of per-ad reporting; a single auto-generated ad per ad group under AI Max. | R32: Strong | S32: PASS
A33: 32 | B33: Headline count & pinning for compliance-heavy verticals | C33: RSA & ad copy | D33: Strategy | E33: Search | F33: Setup | G33: Any | H33: One-off | I33: P3 | J33: Finance/health/legal clients needing fixed disclaimers | K33: Practitioner method | L33: Done | N33: skills/32-compliance-pinning/ | P33: 2026-10-13 | Q33: Change to which slots are always shown (H1/H2/D1); a native advertiser-controlled disclaimer field for Search RSAs; AI Max text customisation becoming mandatory or ignoring text guidelines. | R33: Strong | S33: PASS
A34: 33 | B34: Ad copy localisation vs. translation (Nordic patterns) | C34: RSA & ad copy | D34: Technique | E34: All | F34: Setup | G34: Any | H34: As needed | I34: P2 | J34: Expanding to SE/NO/DK/FI or localising English-first copy | K34: Epiminds method | L34: Drafting | N34: skills/33-nordic-localisation/ | O34: THIN CANON stub — see SKILL.md question for Elias | P34: 2026-10-13 | Q34: Not applicable until a method exists; adjacent findings depend on the 30/90 character limits. | R34: Thin | S34: NEEDS ELIAS
A35: 34 | B35: Improve Expected CTR | C35: Quality Score | D35: Technique | E35: Search | F35: Optimise | G35: Any | H35: As needed | I35: P1 | J35: Expected CTR below average on spend-heavy keywords | K35: Epiminds method | L35: Done | N35: skills/34-improve-expected-ctr/ | P35: 2026-10-13 | Q35: Google changing the expected-CTR comparison set (currently exact-same-keyword, trailing 90 days) or folding assets into QS; retirement of keyword-level QS reporting. | R35: Strong | S35: PASS
A36: 35 | B36: Improve Ad Relevance | C36: Quality Score | D36: Technique | E36: Search | F36: Optimise | G36: Any | H36: As needed | I36: P1 | J36: Ad relevance below average; keyword-to-ad mismatch | K36: Epiminds method | L36: Done | N36: skills/35-improve-ad-relevance/ | P36: 2026-10-13 | Q36: Google merging ad relevance into an asset-level signal, changing the exact-same-keyword comparison set, or removing keyword-level component reporting. | R36: Adequate | S36: PASS
A37: 36 | B37: Improve Landing Page Experience | C37: Quality Score | D37: Technique | E37: Search | F37: Optimise | G37: Any | H37: As needed | I37: P1 | J37: LPE below average; CPCs high relative to competitors | K37: Epiminds method | L37: Done | N37: skills/36-improve-landing-page-experience/ | P37: 2026-10-13 | Q37: Google replacing crawler-based LPE with a separately reported Core Web Vitals or engagement signal, removing LPE from the keyword report, or changing the exact-same-keyword comparison set. | R37: Adequate | S37: PASS
A38: 37 | B38: QS tracker script (daily snapshot) | C38: Quality Score | D38: Script | E38: Search | F38: Setup | G38: Any | H38: One-off | I38: P2 | J38: Need QS history, which Google doesn't keep | K38: Brainlabs / Optmyzr | L38: Done | N38: skills/37-qs-tracker-script/ | P38: 2026-10-13 | Q38: Removal of quality_info from the Google Ads API/Scripts reports, a change to the Scripts 30-minute execution limit, or Google shipping native impression-weighted QS trend charts. | R38: Strong | S38: PASS
A39: 38 | B39: Impression-weighted QS as the account metric | C39: Quality Score | D39: Technique | E39: Search | F39: Diagnose | G39: Any | H39: Monthly | I39: P2 | J39: Reporting QS; average QS is misleading | K39: Practitioner method | L39: Done | N39: skills/38-impression-weighted-qs/ | P39: 2026-10-13 | Q39: Google publishing a native weighted account-level quality metric, removing keyword-level QS, or changing the null-QS rule. | R39: Strong | S39: PASS
A40: 39 | B40: Does QS matter under Smart Bidding — the evidence | C40: Quality Score | D40: Research | E40: Search | F40: Optimise | G40: Any | H40: One-off | I40: P3 | J40: Deciding how much effort to put into QS work | K40: Practitioner debate | L40: Done | N40: skills/39-qs-under-smart-bidding/ | P40: 2026-10-13 | Q40: Google publishing how Smart Bidding treats quality components, a canon cross-account study of QS work under Smart Bidding, or removal of keyword-level QS. | R40: Adequate | S40: PASS
A41: 40 | B41: Portfolio bid strategies with max CPC caps | C41: Bidding | D41: Technique | E41: Search | F41: Optimise | G41: Established | H41: One-off | I41: P1 | J41: Smart Bidding overpaying on clicks; need a ceiling | K41: Google docs + practitioner | L41: Done | N41: skills/40-portfolio-max-cpc-caps/ | P41: 2026-10-13 | Q41: Google adding bid limits to standard (non-portfolio) strategies, removing them from portfolios, extending them beyond Search auctions, or reversing the 17 Aug 2026 budget-limited bidding change. | R41: Strong | S41: PASS
A42: 41 | B42: Conversion value rules | C42: Bidding | D42: Technique | E42: All | F42: Optimise | G42: Established | H42: One-off | I42: P2 | J42: Want tROAS to favour an audience/location/device without splitting campaigns | K42: Google docs + practitioner | L42: Done | N42: skills/41-conversion-value-rules/ | P42: 2026-10-13 | Q42: Google changing the multiplier range (0.5–10×), the two-dimension limit, the one-rule-per-conversion precedence, or extending rules to non-value bid strategies. | R42: Adequate | S42: PASS
A43: 42 | B43: Value-based bidding for lead gen (proxy values) | C43: Bidding | D43: Strategy | E43: All | F43: Scale | G43: Established | H43: One-off | I43: P1 | J43: Lead-gen client; leads differ in quality; moving from tCPA to tROAS | K43: Practitioner method | L43: Done | N43: skills/42-value-based-bidding-lead-gen/ | P43: 2026-10-13 | Q43: Google changing conversion value rules, removing Max Conversion Value without a target, changing tROAS eligibility floors, or the Data Manager API changing offline value upload. | R43: Strong | S43: PASS
A44: 43 | B44: Micro-conversion ladder for new accounts | C44: Bidding | D44: Strategy | E44: All | F44: Setup | G44: New | H44: One-off | I44: P1 | J44: Too few macro conversions for Smart Bidding to learn | K44: Practitioner method | L44: Done | N44: skills/43-micro-conversion-ladder/ | P44: 2026-10-13 | Q44: Google removing the primary/secondary conversion distinction, changing the Smart Bidding data floors, or retiring Maximize Clicks. | R44: Adequate | S44: PASS
A45: 44 | B45: Seasonality adjustments vs. data exclusions | C45: Bidding | D45: Technique | E45: All | F45: Optimise | G45: Established | H45: As needed | I45: P2 | J45: Short sale coming, or a tracking outage happened | K45: Google docs + practitioner | L45: Done | N45: skills/44-seasonality-adjustments-vs-data-exclusions/ | P45: 2026-10-13 | Q45: Google changing seasonality-adjustment duration guidance or the 0.1–10 modifier range, changing data exclusions to conversion-based rather than click-based, or new cross-account evidence that adjustments on mainstream events stopped inflating CPCs. | R45: Strong | S45: PASS
A46: 45 | B46: Target impression share for brand defence | C46: Bidding | D46: Strategy | E46: Search | F46: Protect | G46: Any | H46: One-off | I46: P2 | J46: Competitors bidding on brand; deciding how to defend | K46: Practitioner method | L46: Done | N46: skills/45-target-impression-share-brand-defence/ | P46: 2026-10-13 | Q46: Google removing the bid limit from Target Impression Share, changing Ad Rank reserve pricing on uncontested auctions, or restricting competitor brand bidding by policy. | R46: Strong | S46: PASS
... A53: 52 | B53: B2B audience exclusions (demographic, in-market, HHI) | C53: Audiences | D53: Technique | E53: All | F53: Optimise | G53: Any | H53: As needed | I53: P2 | J53: B2B client getting consumer traffic | K53: Practitioner method | L53: Done | N53: skills/52-b2b-audience-exclusions/ | P53: 2026-10-13 | Q53: Google adding parental status, life events or custom segments to Search; HHI becoming available in European markets; Smart Bidding honouring non-(-100%) audience bid adjustments; demographics gaining an observation setting. | R53: Adequate | S53: PASS
A54: 53 | B54: Combined segments for intent stacking | C54: Audiences | D54: Technique | E54: All | F54: Optimise | G54: Established | H54: As needed | I54: P3 | J54: Want AND/OR/NOT audience logic for tighter targeting | K54: Google docs + practitioner | L54: Drafting | N54: skills/53-combined-segments-intent-stacking/ | O54: THIN CANON stub — see SKILL.md question for Elias | P54: 2026-10-13 | Q54: Any change to combined-segment availability by campaign type or to the AND/OR/NOT rules; Search gaining custom segments. | R54: Thin | S54: NEEDS ELIAS
A55: 54 | B55: GA4 first-party segments into Google Ads | C55: Audiences | D55: Technique | E55: All | F55: Setup | G55: Any | H55: One-off | I55: P2 | J55: GA4 linked; want behavioural segments as signals | K55: Google docs + practitioner | L55: Done | N55: skills/54-ga4-segments-into-google-ads/ | P55: 2026-10-13 | Q55: GA4 removing the 30-day backfill or changing the 100-audience cap; GA4 Customer Match leaving beta with different mechanics; Google Ads deprecating tag-based remarketing lists; consent-mode changes to which GA4 users are exportable. | R55: Adequate | S55: PASS
A56: 55 | B56: PMax brand exclusions — full method | C56: Performance Max | D56: Technique | E56: PMax | F56: Protect | G56: Any | H56: One-off | I56: P1 | J56: PMax eating brand traffic and inflating ROAS | K56: Google docs + practitioner | L56: Done | N56: skills/55-pmax-brand-exclusions/ | P56: 2026-10-13 | Q56: Google extending brand exclusions beyond Search, Shopping and YouTube-search inventory; a change to broad-match-based brand-list matching; removal of the "Allow Shopping ads on excluded brand searches" option; a change to the exact-match-keyword priority rule between Search and PMax. | R56: Strong | S56: PASS
A57: 56 | B57: Feed-only PMax | C57: Performance Max | D57: Strategy | E57: PMax | F57: Setup | G57: Any | H57: One-off | I57: P2 | J57: E-com client; want Shopping-like control without creative spend | K57: Practitioner method | L57: Done | N57: skills/56-feed-only-pmax/ | P57: 2026-10-13 | Q57: Google removing the opt-out from auto-generated assets; a change to the channel report's "ads using product data" segmentation; deprecation of Standard Shopping as the comparison campaign. | R57: Adequate | S57: PASS
A58: 57 | B58: PMax search terms insights — what you can see and mine | C58: Performance Max | D58: Diagnostic | E58: PMax | F58: Optimise | G58: Any | H58: Monthly | I58: P1 | J58: Need query-level visibility in PMax | K58: Google docs + practitioner | L58: Done | N58: skills/57-pmax-search-terms-insights/ | P58: 2026-10-13 | Q58: Google adding cost to term-level PMax reporting; removal of the PMax search terms report or the campaign_search_term_insight API resource; asset-group-level negatives; a change to the privacy threshold that withholds low-volume terms. | R58: Strong | S58: PASS
A59: 58 | B59: Asset groups by product vs. by audience | C59: Performance Max | D59: Strategy | E59: PMax | F59: Setup | G59: Any | H59: One-off | I59: P2 | J59: Structuring a new PMax campaign | K59: Practitioner debate | L59: Done | N59: skills/58-pmax-asset-group-structure/ | P59: 2026-10-13 | Q59: Google making audience signals hard targets; asset-group-level bidding targets; changes to listing-group mechanics. | R59: Adequate | S59: PASS
A60: 59 | B60: PMax cannibalising brand/Search — diagnosis | C60: Performance Max | D60: Diagnostic | E60: PMax | F60: Diagnose | G60: Established | H60: Monthly | I60: P1 | J60: Search performance fell after PMax launch | K60: Mike Rhodes script + practitioner | L60: Done | N60: skills/59-pmax-cannibalisation-diagnosis/ | P60: 2026-10-13 | Q60: A change to the rule that an identical Search keyword takes precedence over PMax; cost appearing in the PMax search terms report; Google shipping Search-vs-PMax or channel-level controls; removal of the PMax search terms report. | R60: Strong | S60: PASS
A61: 60 | B61: PMax placement exclusions & display/video spend | C61: Performance Max | D61: Technique | E61: PMax | F61: Optimise | G61: Any | H61: Monthly | I61: P2 | J61: Too much PMax spend going to low-quality placements | K61: Practitioner method | L61: Done | N61: skills/60-pmax-placement-exclusions/ | P61: 2026-10-13 | Q61: Campaign-level placement exclusions or channel-level budget/bid controls in PMax; cost appearing in the PMax placement report; a change to the account-level exclusion scope. | R61: Strong | S61: PASS
A62: 61 | B62: URL expansion off + final URL control | C62: Performance Max | D62: Setting | E62: PMax | F62: Setup | G62: Any | H62: One-off | I62: P2 | J62: PMax sending traffic to unintended pages | K62: Google docs + practitioner | L62: Done | N62: skills/61-pmax-url-expansion/ | P62: 2026-10-13 | Q62: A change to the default-on setting; the ability to exclude the campaign's own final URL or homepage; expansion folding into AI Max page controls; removal of page feeds from PMax. | R62: Adequate | S62: PASS
A63: 62 | B63: PMax campaign-level negatives | C63: Performance Max | D63: Technique | E63: PMax | F63: Optimise | G63: Any | H63: As needed | I63: P1 | J63: Irrelevant queries visible in PMax insights | K63: Google docs (recent feature) | L63: Done | N63: skills/62-pmax-campaign-negatives/ | P63: 2026-10-13 | Q63: PMax negatives extending to Display, Video or Discover inventory; asset-group-level negatives; a change to the 10,000-per-campaign or 1,000-per-account limits; removal of the PMax search terms report. | R63: Strong | S63: PASS
A64: 63 | B64: New customer acquisition goal — definition problem | C64: Performance Max | D64: Strategy | E64: PMax | F64: Scale | G64: Established | H64: One-off | I64: P3 | J64: Client wants to bid higher for new customers | K64: Google docs + practitioner | L64: Done | N64: skills/63-pmax-new-customer-acquisition/ | P64: 2026-10-13 | Q64: A change to the 540-day auto-detection window; removal of the Original conv. value column; the premium becoming bidding-only (non-reporting); in-platform incrementality testing for lifecycle goals; removal of New Customer Only mode. | R64: Adequate | S64: PASS
A65: 64 | B65: Custom labels by margin / stock / seasonality | C65: Shopping & feeds | D65: Technique | E65: Shopping | F65: Optimise | G65: Established | H65: One-off | I65: P1 | J65: Want bidding tiers by profitability or availability | K65: Practitioner method | L65: Done | N65: skills/64-custom-labels-margin-stock-season/ | P65: 2026-10-13 | Q65: Google changing the 5-label or 1,000-value caps, removing custom labels from PMax/AI Max listing groups, or dropping supplemental data sources from Merchant Center Next. | R65: Strong | S65: PASS
A66: 65 | B66: Feed rules & supplemental feeds | C66: Shopping & feeds | D66: Technique | E66: Shopping | F66: Optimise | G66: Any | H66: As needed | I66: P2 | J66: Need to change titles/attributes without touching the source feed | K66: Google docs + practitioner | L66: Done | N66: skills/65-feed-rules-supplemental-feeds/ | P66: 2026-10-13 | Q66: Google removing supplemental sources or attribute rules from Merchant Center Next, dropping the Advanced data source management add-on, making id matching case-insensitive, or lifting the once-a-day scheduled-fetch limit. | R66: Adequate | S66: PASS
... A91: 90 | B91: Account-level negatives & brand restrictions | C91: Defaults to override | D91: Setting | E91: All | F91: Protect | G91: Any | H91: One-off | I91: P1 | J91: Account-wide exclusions needed across many campaigns | K91: Google docs (recent feature) | L91: Done | N91: skills/90-account-level-negatives-brand-restrictions/ | P91: 2026-10-13 | Q91: The 1,000-keyword account-level cap changing; account-level negatives gaining per-campaign-type scoping; brand exclusions reliably covering close variants (new cross-account evidence); PMax negatives at asset-group level. | R91: Adequate | S91: PASS

Sheet Tag legend
A1: Column | B1: Tag | C1: Meaning
A2: Type | B2: Structure | C2: How to organise campaigns/ad groups
A3: Type | B3: Strategy | C3: A choice between approaches, with the decision rule
A4: Type | B4: Technique | C4: A specific method to apply
A5: Type | B5: Script | C5: A Google Ads Script to install and read
A6: Type | B6: Research | C6: Evidence/study that changes what you do
A7: Type | B7: Diagnostic | C7: How to find out what's wrong
A8: Type | B8: Setting | C8: A default to override, and why
A9: Campaign type | B9: Search / Shopping / PMax / All | C9: Which campaign type it applies to
A10: Phase | B10: Setup | C10: Building or restructuring
A11: Phase | B11: Scale | C11: Growing volume once the base works
A12: Phase | B12: Optimise | C12: Ongoing improvement of a working account
... A25: Review | B25: PASS / FAIL / NEEDS ELIAS | C25: Blind rubric review result

Sheet Summary
A1: Category | B1: Count | C1: Done | E1: Priority | F1: Count | H1: Phase | I1: Count
A2: Account structure | B2: =COUNTIF(Skills!$C$2:$C$91,A2) | C2: =COUNTIFS(Skills!$C$2:$C$91,A2,Skills!$L$2:$L$91,"Done") | E2: P1 | F2: =COUNTIF(Skills!$I$2:$I$91,E2) | H2: Setup | I2: =COUNTIF(Skills!$F$2:$F$91,H2)
A3: Keyword & query | B3: =COUNTIF(Skills!$C$2:$C$91,A3) | C3: =COUNTIFS(Skills!$C$2:$C$91,A3,Skills!$L$2:$L$91,"Done") | E3: P2 | F3: =COUNTIF(Skills!$I$2:$I$91,E3) | H3: Scale | I3: =COUNTIF(Skills!$F$2:$F$91,H3)
A4: RSA & ad copy | B4: =COUNTIF(Skills!$C$2:$C$91,A4) | C4: =COUNTIFS(Skills!$C$2:$C$91,A4,Skills!$L$2:$L$91,"Done") | E4: P3 | F4: =COUNTIF(Skills!$I$2:$I$91,E4) | H4: Optimise | I4: =COUNTIF(Skills!$F$2:$F$91,H4)
A5: Quality Score | B5: =COUNTIF(Skills!$C$2:$C$91,A5) | C5: =COUNTIFS(Skills!$C$2:$C$91,A5,Skills!$L$2:$L$91,"Done") | H5: Diagnose | I5: =COUNTIF(Skills!$F$2:$F$91,H5)
A6: Bidding | B6: =COUNTIF(Skills!$C$2:$C$91,A6) | C6: =COUNTIFS(Skills!$C$2:$C$91,A6,Skills!$L$2:$L$91,"Done") | H6: Protect | I6: =COUNTIF(Skills!$F$2:$F$91,H6)
A7: Audiences | B7: =COUNTIF(Skills!$C$2:$C$91,A7) | C7: =COUNTIFS(Skills!$C$2:$C$91,A7,Skills!$L$2:$L$91,"Done")
A8: Performance Max | B8: =COUNTIF(Skills!$C$2:$C$91,A8) | C8: =COUNTIFS(Skills!$C$2:$C$91,A8,Skills!$L$2:$L$91,"Done")
A9: Shopping & feeds | B9: =COUNTIF(Skills!$C$2:$C$91,A9) | C9: =COUNTIFS(Skills!$C$2:$C$91,A9,Skills!$L$2:$L$91,"Done")
A10: Scripts & automation | B10: =COUNTIF(Skills!$C$2:$C$91,A10) | C10: =COUNTIFS(Skills!$C$2:$C$91,A10,Skills!$L$2:$L$91,"Done")
A11: Testing & measurement | B11: =COUNTIF(Skills!$C$2:$C$91,A11) | C11: =COUNTIFS(Skills!$C$2:$C$91,A11,Skills!$L$2:$L$91,"Done")
A12: Defaults to override | B12: =COUNTIF(Skills!$C$2:$C$91,A12) | C12: =COUNTIFS(Skills!$C$2:$C$91,A12,Skills!$L$2:$L$91,"Done")
A13: Total | B13: =SUM(B2:B12) | C13: =SUM(C2:C12)
